{
  "type": "Program",
  "body": [
    {
      "type": "ExportNamedDeclaration",
      "declaration": {
        "type": "FunctionDeclaration",
        "id": {
          "type": "Identifier",
          "name": "rotate_right",
          "range": [
            287,
            299
          ],
          "loc": {
            "start": {
              "line": 14,
              "column": 16
            },
            "end": {
              "line": 14,
              "column": 28
            }
          }
        },
        "params": [
          {
            "type": "Identifier",
            "name": "B",
            "range": [
              302,
              303
            ],
            "loc": {
              "start": {
                "line": 14,
                "column": 31
              },
              "end": {
                "line": 14,
                "column": 32
              }
            }
          }
        ],
        "body": {
          "type": "BlockStatement",
          "body": [
            {
              "type": "VariableDeclaration",
              "declarations": [
                {
                  "type": "VariableDeclarator",
                  "id": {
                    "type": "Identifier",
                    "name": "A",
                    "range": [
                      316,
                      317
                    ],
                    "loc": {
                      "start": {
                        "line": 16,
                        "column": 7
                      },
                      "end": {
                        "line": 16,
                        "column": 8
                      }
                    }
                  },
                  "init": {
                    "type": "MemberExpression",
                    "computed": false,
                    "object": {
                      "type": "Identifier",
                      "name": "B",
                      "range": [
                        320,
                        321
                      ],
                      "loc": {
                        "start": {
                          "line": 16,
                          "column": 11
                        },
                        "end": {
                          "line": 16,
                          "column": 12
                        }
                      }
                    },
                    "property": {
                      "type": "Identifier",
                      "name": "left",
                      "range": [
                        322,
                        326
                      ],
                      "loc": {
                        "start": {
                          "line": 16,
                          "column": 13
                        },
                        "end": {
                          "line": 16,
                          "column": 17
                        }
                      }
                    },
                    "range": [
                      320,
                      326
                    ],
                    "loc": {
                      "start": {
                        "line": 16,
                        "column": 11
                      },
                      "end": {
                        "line": 16,
                        "column": 17
                      }
                    }
                  },
                  "range": [
                    316,
                    326
                  ],
                  "loc": {
                    "start": {
                      "line": 16,
                      "column": 7
                    },
                    "end": {
                      "line": 16,
                      "column": 17
                    }
                  }
                }
              ],
              "kind": "const",
              "range": [
                310,
                327
              ],
              "loc": {
                "start": {
                  "line": 16,
                  "column": 1
                },
                "end": {
                  "line": 16,
                  "column": 18
                }
              }
            },
            {
              "type": "VariableDeclaration",
              "declarations": [
                {
                  "type": "VariableDeclarator",
                  "id": {
                    "type": "Identifier",
                    "name": "a",
                    "range": [
                      335,
                      336
                    ],
                    "loc": {
                      "start": {
                        "line": 17,
                        "column": 7
                      },
                      "end": {
                        "line": 17,
                        "column": 8
                      }
                    }
                  },
                  "init": {
                    "type": "MemberExpression",
                    "computed": false,
                    "object": {
                      "type": "Identifier",
                      "name": "A",
                      "range": [
                        339,
                        340
                      ],
                      "loc": {
                        "start": {
                          "line": 17,
                          "column": 11
                        },
                        "end": {
                          "line": 17,
                          "column": 12
                        }
                      }
                    },
                    "property": {
                      "type": "Identifier",
                      "name": "left",
                      "range": [
                        341,
                        345
                      ],
                      "loc": {
                        "start": {
                          "line": 17,
                          "column": 13
                        },
                        "end": {
                          "line": 17,
                          "column": 17
                        }
                      }
                    },
                    "range": [
                      339,
                      345
                    ],
                    "loc": {
                      "start": {
                        "line": 17,
                        "column": 11
                      },
                      "end": {
                        "line": 17,
                        "column": 17
                      }
                    }
                  },
                  "range": [
                    335,
                    345
                  ],
                  "loc": {
                    "start": {
                      "line": 17,
                      "column": 7
                    },
                    "end": {
                      "line": 17,
                      "column": 17
                    }
                  }
                }
              ],
              "kind": "const",
              "range": [
                329,
                347
              ],
              "loc": {
                "start": {
                  "line": 17,
                  "column": 1
                },
                "end": {
                  "line": 17,
                  "column": 19
                }
              }
            },
            {
              "type": "VariableDeclaration",
              "declarations": [
                {
                  "type": "VariableDeclarator",
                  "id": {
                    "type": "Identifier",
                    "name": "b",
                    "range": [
                      355,
                      356
                    ],
                    "loc": {
                      "start": {
                        "line": 18,
                        "column": 7
                      },
                      "end": {
                        "line": 18,
                        "column": 8
                      }
                    }
                  },
                  "init": {
                    "type": "MemberExpression",
                    "computed": false,
                    "object": {
                      "type": "Identifier",
                      "name": "A",
                      "range": [
                        359,
                        360
                      ],
                      "loc": {
                        "start": {
                          "line": 18,
                          "column": 11
                        },
                        "end": {
                          "line": 18,
                          "column": 12
                        }
                      }
                    },
                    "property": {
                      "type": "Identifier",
                      "name": "right",
                      "range": [
                        361,
                        366
                      ],
                      "loc": {
                        "start": {
                          "line": 18,
                          "column": 13
                        },
                        "end": {
                          "line": 18,
                          "column": 18
                        }
                      }
                    },
                    "range": [
                      359,
                      366
                    ],
                    "loc": {
                      "start": {
                        "line": 18,
                        "column": 11
                      },
                      "end": {
                        "line": 18,
                        "column": 18
                      }
                    }
                  },
                  "range": [
                    355,
                    366
                  ],
                  "loc": {
                    "start": {
                      "line": 18,
                      "column": 7
                    },
                    "end": {
                      "line": 18,
                      "column": 18
                    }
                  }
                }
              ],
              "kind": "const",
              "range": [
                349,
                368
              ],
              "loc": {
                "start": {
                  "line": 18,
                  "column": 1
                },
                "end": {
                  "line": 18,
                  "column": 20
                }
              }
            },
            {
              "type": "VariableDeclaration",
              "declarations": [
                {
                  "type": "VariableDeclarator",
                  "id": {
                    "type": "Identifier",
                    "name": "c",
                    "range": [
                      376,
                      377
                    ],
                    "loc": {
                      "start": {
                        "line": 19,
                        "column": 7
                      },
                      "end": {
                        "line": 19,
                        "column": 8
                      }
                    }
                  },
                  "init": {
                    "type": "MemberExpression",
                    "computed": false,
                    "object": {
                      "type": "Identifier",
                      "name": "B",
                      "range": [
                        380,
                        381
                      ],
                      "loc": {
                        "start": {
                          "line": 19,
                          "column": 11
                        },
                        "end": {
                          "line": 19,
                          "column": 12
                        }
                      }
                    },
                    "property": {
                      "type": "Identifier",
                      "name": "right",
                      "range": [
                        382,
                        387
                      ],
                      "loc": {
                        "start": {
                          "line": 19,
                          "column": 13
                        },
                        "end": {
                          "line": 19,
                          "column": 18
                        }
                      }
                    },
                    "range": [
                      380,
                      387
                    ],
                    "loc": {
                      "start": {
                        "line": 19,
                        "column": 11
                      },
                      "end": {
                        "line": 19,
                        "column": 18
                      }
                    }
                  },
                  "range": [
                    376,
                    387
                  ],
                  "loc": {
                    "start": {
                      "line": 19,
                      "column": 7
                    },
                    "end": {
                      "line": 19,
                      "column": 18
                    }
                  }
                }
              ],
              "kind": "const",
              "range": [
                370,
                389
              ],
              "loc": {
                "start": {
                  "line": 19,
                  "column": 1
                },
                "end": {
                  "line": 19,
                  "column": 20
                }
              }
            },
            {
              "type": "ExpressionStatement",
              "expression": {
                "type": "AssignmentExpression",
                "operator": "=",
                "left": {
                  "type": "ArrayPattern",
                  "elements": [
                    {
                      "type": "MemberExpression",
                      "computed": false,
                      "object": {
                        "type": "Identifier",
                        "name": "A",
                        "range": [
                          393,
                          394
                        ],
                        "loc": {
                          "start": {
                            "line": 21,
                            "column": 2
                          },
                          "end": {
                            "line": 21,
                            "column": 3
                          }
                        }
                      },
                      "property": {
                        "type": "Identifier",
                        "name": "value",
                        "range": [
                          395,
                          400
                        ],
                        "loc": {
                          "start": {
                            "line": 21,
                            "column": 4
                          },
                          "end": {
                            "line": 21,
                            "column": 9
                          }
                        }
                      },
                      "range": [
                        393,
                        400
                      ],
                      "loc": {
                        "start": {
                          "line": 21,
                          "column": 2
                        },
                        "end": {
                          "line": 21,
                          "column": 9
                        }
                      }
                    },
                    {
                      "type": "MemberExpression",
                      "computed": false,
                      "object": {
                        "type": "Identifier",
                        "name": "B",
                        "range": [
                          403,
                          404
                        ],
                        "loc": {
                          "start": {
                            "line": 21,
                            "column": 12
                          },
                          "end": {
                            "line": 21,
                            "column": 13
                          }
                        }
                      },
                      "property": {
                        "type": "Identifier",
                        "name": "value",
                        "range": [
                          405,
                          410
                        ],
                        "loc": {
                          "start": {
                            "line": 21,
                            "column": 14
                          },
                          "end": {
                            "line": 21,
                            "column": 19
                          }
                        }
                      },
                      "range": [
                        403,
                        410
                      ],
                      "loc": {
                        "start": {
                          "line": 21,
                          "column": 12
                        },
                        "end": {
                          "line": 21,
                          "column": 19
                        }
                      }
                    }
                  ],
                  "range": [
                    392,
                    411
                  ],
                  "loc": {
                    "start": {
                      "line": 21,
                      "column": 1
                    },
                    "end": {
                      "line": 21,
                      "column": 20
                    }
                  }
                },
                "right": {
                  "type": "ArrayExpression",
                  "elements": [
                    {
                      "type": "MemberExpression",
                      "computed": false,
                      "object": {
                        "type": "Identifier",
                        "name": "B",
                        "range": [
                          415,
                          416
                        ],
                        "loc": {
                          "start": {
                            "line": 21,
                            "column": 24
                          },
                          "end": {
                            "line": 21,
                            "column": 25
                          }
                        }
                      },
                      "property": {
                        "type": "Identifier",
                        "name": "value",
                        "range": [
                          417,
                          422
                        ],
                        "loc": {
                          "start": {
                            "line": 21,
                            "column": 26
                          },
                          "end": {
                            "line": 21,
                            "column": 31
                          }
                        }
                      },
                      "range": [
                        415,
                        422
                      ],
                      "loc": {
                        "start": {
                          "line": 21,
                          "column": 24
                        },
                        "end": {
                          "line": 21,
                          "column": 31
                        }
                      }
                    },
                    {
                      "type": "MemberExpression",
                      "computed": false,
                      "object": {
                        "type": "Identifier",
                        "name": "A",
                        "range": [
                          425,
                          426
                        ],
                        "loc": {
                          "start": {
                            "line": 21,
                            "column": 34
                          },
                          "end": {
                            "line": 21,
                            "column": 35
                          }
                        }
                      },
                      "property": {
                        "type": "Identifier",
                        "name": "value",
                        "range": [
                          427,
                          432
                        ],
                        "loc": {
                          "start": {
                            "line": 21,
                            "column": 36
                          },
                          "end": {
                            "line": 21,
                            "column": 41
                          }
                        }
                      },
                      "range": [
                        425,
                        432
                      ],
                      "loc": {
                        "start": {
                          "line": 21,
                          "column": 34
                        },
                        "end": {
                          "line": 21,
                          "column": 41
                        }
                      }
                    }
                  ],
                  "range": [
                    414,
                    433
                  ],
                  "loc": {
                    "start": {
                      "line": 21,
                      "column": 23
                    },
                    "end": {
                      "line": 21,
                      "column": 42
                    }
                  }
                },
                "range": [
                  392,
                  433
                ],
                "loc": {
                  "start": {
                    "line": 21,
                    "column": 1
                  },
                  "end": {
                    "line": 21,
                    "column": 42
                  }
                }
              },
              "range": [
                392,
                435
              ],
              "loc": {
                "start": {
                  "line": 21,
                  "column": 1
                },
                "end": {
                  "line": 21,
                  "column": 44
                }
              }
            },
            {
              "type": "ExpressionStatement",
              "expression": {
                "type": "AssignmentExpression",
                "operator": "=",
                "left": {
                  "type": "ArrayPattern",
                  "elements": [
                    {
                      "type": "MemberExpression",
                      "computed": false,
                      "object": {
                        "type": "Identifier",
                        "name": "A",
                        "range": [
                          438,
                          439
                        ],
                        "loc": {
                          "start": {
                            "line": 22,
                            "column": 2
                          },
                          "end": {
                            "line": 22,
                            "column": 3
                          }
                        }
                      },
                      "property": {
                        "type": "Identifier",
                        "name": "color",
                        "range": [
                          440,
                          445
                        ],
                        "loc": {
                          "start": {
                            "line": 22,
                            "column": 4
                          },
                          "end": {
                            "line": 22,
                            "column": 9
                          }
                        }
                      },
                      "range": [
                        438,
                        445
                      ],
                      "loc": {
                        "start": {
                          "line": 22,
                          "column": 2
                        },
                        "end": {
                          "line": 22,
                          "column": 9
                        }
                      }
                    },
                    {
                      "type": "MemberExpression",
                      "computed": false,
                      "object": {
                        "type": "Identifier",
                        "name": "B",
                        "range": [
                          448,
                          449
                        ],
                        "loc": {
                          "start": {
                            "line": 22,
                            "column": 12
                          },
                          "end": {
                            "line": 22,
                            "column": 13
                          }
                        }
                      },
                      "property": {
                        "type": "Identifier",
                        "name": "color",
                        "range": [
                          450,
                          455
                        ],
                        "loc": {
                          "start": {
                            "line": 22,
                            "column": 14
                          },
                          "end": {
                            "line": 22,
                            "column": 19
                          }
                        }
                      },
                      "range": [
                        448,
                        455
                      ],
                      "loc": {
                        "start": {
                          "line": 22,
                          "column": 12
                        },
                        "end": {
                          "line": 22,
                          "column": 19
                        }
                      }
                    }
                  ],
                  "range": [
                    437,
                    456
                  ],
                  "loc": {
                    "start": {
                      "line": 22,
                      "column": 1
                    },
                    "end": {
                      "line": 22,
                      "column": 20
                    }
                  }
                },
                "right": {
                  "type": "ArrayExpression",
                  "elements": [
                    {
                      "type": "MemberExpression",
                      "computed": false,
                      "object": {
                        "type": "Identifier",
                        "name": "B",
                        "range": [
                          460,
                          461
                        ],
                        "loc": {
                          "start": {
                            "line": 22,
                            "column": 24
                          },
                          "end": {
                            "line": 22,
                            "column": 25
                          }
                        }
                      },
                      "property": {
                        "type": "Identifier",
                        "name": "color",
                        "range": [
                          462,
                          467
                        ],
                        "loc": {
                          "start": {
                            "line": 22,
                            "column": 26
                          },
                          "end": {
                            "line": 22,
                            "column": 31
                          }
                        }
                      },
                      "range": [
                        460,
                        467
                      ],
                      "loc": {
                        "start": {
                          "line": 22,
                          "column": 24
                        },
                        "end": {
                          "line": 22,
                          "column": 31
                        }
                      }
                    },
                    {
                      "type": "MemberExpression",
                      "computed": false,
                      "object": {
                        "type": "Identifier",
                        "name": "A",
                        "range": [
                          470,
                          471
                        ],
                        "loc": {
                          "start": {
                            "line": 22,
                            "column": 34
                          },
                          "end": {
                            "line": 22,
                            "column": 35
                          }
                        }
                      },
                      "property": {
                        "type": "Identifier",
                        "name": "color",
                        "range": [
                          472,
                          477
                        ],
                        "loc": {
                          "start": {
                            "line": 22,
                            "column": 36
                          },
                          "end": {
                            "line": 22,
                            "column": 41
                          }
                        }
                      },
                      "range": [
                        470,
                        477
                      ],
                      "loc": {
                        "start": {
                          "line": 22,
                          "column": 34
                        },
                        "end": {
                          "line": 22,
                          "column": 41
                        }
                      }
                    }
                  ],
                  "range": [
                    459,
                    478
                  ],
                  "loc": {
                    "start": {
                      "line": 22,
                      "column": 23
                    },
                    "end": {
                      "line": 22,
                      "column": 42
                    }
                  }
                },
                "range": [
                  437,
                  478
                ],
                "loc": {
                  "start": {
                    "line": 22,
                    "column": 1
                  },
                  "end": {
                    "line": 22,
                    "column": 42
                  }
                }
              },
              "range": [
                437,
                480
              ],
              "loc": {
                "start": {
                  "line": 22,
                  "column": 1
                },
                "end": {
                  "line": 22,
                  "column": 44
                }
              }
            },
            {
              "type": "ExpressionStatement",
              "expression": {
                "type": "AssignmentExpression",
                "operator": "=",
                "left": {
                  "type": "MemberExpression",
                  "computed": false,
                  "object": {
                    "type": "Identifier",
                    "name": "B",
                    "range": [
                      483,
                      484
                    ],
                    "loc": {
                      "start": {
                        "line": 24,
                        "column": 1
                      },
                      "end": {
                        "line": 24,
                        "column": 2
                      }
                    }
                  },
                  "property": {
                    "type": "Identifier",
                    "name": "left",
                    "range": [
                      485,
                      489
                    ],
                    "loc": {
                      "start": {
                        "line": 24,
                        "column": 3
                      },
                      "end": {
                        "line": 24,
                        "column": 7
                      }
                    }
                  },
                  "range": [
                    483,
                    489
                  ],
                  "loc": {
                    "start": {
                      "line": 24,
                      "column": 1
                    },
                    "end": {
                      "line": 24,
                      "column": 7
                    }
                  }
                },
                "right": {
                  "type": "Identifier",
                  "name": "a",
                  "range": [
                    492,
                    493
                  ],
                  "loc": {
                    "start": {
                      "line": 24,
                      "column": 10
                    },
                    "end": {
                      "line": 24,
                      "column": 11
                    }
                  }
                },
                "range": [
                  483,
                  493
                ],
                "loc": {
                  "start": {
                    "line": 24,
                    "column": 1
                  },
                  "end": {
                    "line": 24,
                    "column": 11
                  }
                }
              },
              "range": [
                483,
                495
              ],
              "loc": {
                "start": {
                  "line": 24,
                  "column": 1
                },
                "end": {
                  "line": 24,
                  "column": 13
                }
              }
            },
            {
              "type": "ExpressionStatement",
              "expression": {
                "type": "AssignmentExpression",
                "operator": "=",
                "left": {
                  "type": "MemberExpression",
                  "computed": false,
                  "object": {
                    "type": "Identifier",
                    "name": "B",
                    "range": [
                      497,
                      498
                    ],
                    "loc": {
                      "start": {
                        "line": 25,
                        "column": 1
                      },
                      "end": {
                        "line": 25,
                        "column": 2
                      }
                    }
                  },
                  "property": {
                    "type": "Identifier",
                    "name": "right",
                    "range": [
                      499,
                      504
                    ],
                    "loc": {
                      "start": {
                        "line": 25,
                        "column": 3
                      },
                      "end": {
                        "line": 25,
                        "column": 8
                      }
                    }
                  },
                  "range": [
                    497,
                    504
                  ],
                  "loc": {
                    "start": {
                      "line": 25,
                      "column": 1
                    },
                    "end": {
                      "line": 25,
                      "column": 8
                    }
                  }
                },
                "right": {
                  "type": "Identifier",
                  "name": "A",
                  "range": [
                    507,
                    508
                  ],
                  "loc": {
                    "start": {
                      "line": 25,
                      "column": 11
                    },
                    "end": {
                      "line": 25,
                      "column": 12
                    }
                  }
                },
                "range": [
                  497,
                  508
                ],
                "loc": {
                  "start": {
                    "line": 25,
                    "column": 1
                  },
                  "end": {
                    "line": 25,
                    "column": 12
                  }
                }
              },
              "range": [
                497,
                510
              ],
              "loc": {
                "start": {
                  "line": 25,
                  "column": 1
                },
                "end": {
                  "line": 25,
                  "column": 14
                }
              }
            },
            {
              "type": "ExpressionStatement",
              "expression": {
                "type": "AssignmentExpression",
                "operator": "=",
                "left": {
                  "type": "MemberExpression",
                  "computed": false,
                  "object": {
                    "type": "Identifier",
                    "name": "A",
                    "range": [
                      513,
                      514
                    ],
                    "loc": {
                      "start": {
                        "line": 27,
                        "column": 1
                      },
                      "end": {
                        "line": 27,
                        "column": 2
                      }
                    }
                  },
                  "property": {
                    "type": "Identifier",
                    "name": "left",
                    "range": [
                      515,
                      519
                    ],
                    "loc": {
                      "start": {
                        "line": 27,
                        "column": 3
                      },
                      "end": {
                        "line": 27,
                        "column": 7
                      }
                    }
                  },
                  "range": [
                    513,
                    519
                  ],
                  "loc": {
                    "start": {
                      "line": 27,
                      "column": 1
                    },
                    "end": {
                      "line": 27,
                      "column": 7
                    }
                  }
                },
                "right": {
                  "type": "Identifier",
                  "name": "b",
                  "range": [
                    522,
                    523
                  ],
                  "loc": {
                    "start": {
                      "line": 27,
                      "column": 10
                    },
                    "end": {
                      "line": 27,
                      "column": 11
                    }
                  }
                },
                "range": [
                  513,
                  523
                ],
                "loc": {
                  "start": {
                    "line": 27,
                    "column": 1
                  },
                  "end": {
                    "line": 27,
                    "column": 11
                  }
                }
              },
              "range": [
                513,
                525
              ],
              "loc": {
                "start": {
                  "line": 27,
                  "column": 1
                },
                "end": {
                  "line": 27,
                  "column": 13
                }
              }
            },
            {
              "type": "ExpressionStatement",
              "expression": {
                "type": "AssignmentExpression",
                "operator": "=",
                "left": {
                  "type": "MemberExpression",
                  "computed": false,
                  "object": {
                    "type": "Identifier",
                    "name": "A",
                    "range": [
                      527,
                      528
                    ],
                    "loc": {
                      "start": {
                        "line": 28,
                        "column": 1
                      },
                      "end": {
                        "line": 28,
                        "column": 2
                      }
                    }
                  },
                  "property": {
                    "type": "Identifier",
                    "name": "right",
                    "range": [
                      529,
                      534
                    ],
                    "loc": {
                      "start": {
                        "line": 28,
                        "column": 3
                      },
                      "end": {
                        "line": 28,
                        "column": 8
                      }
                    }
                  },
                  "range": [
                    527,
                    534
                  ],
                  "loc": {
                    "start": {
                      "line": 28,
                      "column": 1
                    },
                    "end": {
                      "line": 28,
                      "column": 8
                    }
                  }
                },
                "right": {
                  "type": "Identifier",
                  "name": "c",
                  "range": [
                    537,
                    538
                  ],
                  "loc": {
                    "start": {
                      "line": 28,
                      "column": 11
                    },
                    "end": {
                      "line": 28,
                      "column": 12
                    }
                  }
                },
                "range": [
                  527,
                  538
                ],
                "loc": {
                  "start": {
                    "line": 28,
                    "column": 1
                  },
                  "end": {
                    "line": 28,
                    "column": 12
                  }
                }
              },
              "range": [
                527,
                540
              ],
              "loc": {
                "start": {
                  "line": 28,
                  "column": 1
                },
                "end": {
                  "line": 28,
                  "column": 14
                }
              }
            },
            {
              "type": "ExpressionStatement",
              "expression": {
                "type": "AssignmentExpression",
                "operator": "=",
                "left": {
                  "type": "MemberExpression",
                  "computed": false,
                  "object": {
                    "type": "Identifier",
                    "name": "a",
                    "range": [
                      543,
                      544
                    ],
                    "loc": {
                      "start": {
                        "line": 30,
                        "column": 1
                      },
                      "end": {
                        "line": 30,
                        "column": 2
                      }
                    }
                  },
                  "property": {
                    "type": "Identifier",
                    "name": "parent",
                    "range": [
                      545,
                      551
                    ],
                    "loc": {
                      "start": {
                        "line": 30,
                        "column": 3
                      },
                      "end": {
                        "line": 30,
                        "column": 9
                      }
                    }
                  },
                  "range": [
                    543,
                    551
                  ],
                  "loc": {
                    "start": {
                      "line": 30,
                      "column": 1
                    },
                    "end": {
                      "line": 30,
                      "column": 9
                    }
                  }
                },
                "right": {
                  "type": "Identifier",
                  "name": "B",
                  "range": [
                    554,
                    555
                  ],
                  "loc": {
                    "start": {
                      "line": 30,
                      "column": 12
                    },
                    "end": {
                      "line": 30,
                      "column": 13
                    }
                  }
                },
                "range": [
                  543,
                  555
                ],
                "loc": {
                  "start": {
                    "line": 30,
                    "column": 1
                  },
                  "end": {
                    "line": 30,
                    "column": 13
                  }
                }
              },
              "range": [
                543,
                557
              ],
              "loc": {
                "start": {
                  "line": 30,
                  "column": 1
                },
                "end": {
                  "line": 30,
                  "column": 15
                }
              }
            },
            {
              "type": "ExpressionStatement",
              "expression": {
                "type": "AssignmentExpression",
                "operator": "=",
                "left": {
                  "type": "MemberExpression",
                  "computed": false,
                  "object": {
                    "type": "Identifier",
                    "name": "b",
                    "range": [
                      559,
                      560
                    ],
                    "loc": {
                      "start": {
                        "line": 31,
                        "column": 1
                      },
                      "end": {
                        "line": 31,
                        "column": 2
                      }
                    }
                  },
                  "property": {
                    "type": "Identifier",
                    "name": "parent",
                    "range": [
                      561,
                      567
                    ],
                    "loc": {
                      "start": {
                        "line": 31,
                        "column": 3
                      },
                      "end": {
                        "line": 31,
                        "column": 9
                      }
                    }
                  },
                  "range": [
                    559,
                    567
                  ],
                  "loc": {
                    "start": {
                      "line": 31,
                      "column": 1
                    },
                    "end": {
                      "line": 31,
                      "column": 9
                    }
                  }
                },
                "right": {
                  "type": "Identifier",
                  "name": "A",
                  "range": [
                    570,
                    571
                  ],
                  "loc": {
                    "start": {
                      "line": 31,
                      "column": 12
                    },
                    "end": {
                      "line": 31,
                      "column": 13
                    }
                  }
                },
                "range": [
                  559,
                  571
                ],
                "loc": {
                  "start": {
                    "line": 31,
                    "column": 1
                  },
                  "end": {
                    "line": 31,
                    "column": 13
                  }
                }
              },
              "range": [
                559,
                573
              ],
              "loc": {
                "start": {
                  "line": 31,
                  "column": 1
                },
                "end": {
                  "line": 31,
                  "column": 15
                }
              }
            },
            {
              "type": "ExpressionStatement",
              "expression": {
                "type": "AssignmentExpression",
                "operator": "=",
                "left": {
                  "type": "MemberExpression",
                  "computed": false,
                  "object": {
                    "type": "Identifier",
                    "name": "c",
                    "range": [
                      575,
                      576
                    ],
                    "loc": {
                      "start": {
                        "line": 32,
                        "column": 1
                      },
                      "end": {
                        "line": 32,
                        "column": 2
                      }
                    }
                  },
                  "property": {
                    "type": "Identifier",
                    "name": "parent",
                    "range": [
                      577,
                      583
                    ],
                    "loc": {
                      "start": {
                        "line": 32,
                        "column": 3
                      },
                      "end": {
                        "line": 32,
                        "column": 9
                      }
                    }
                  },
                  "range": [
                    575,
                    583
                  ],
                  "loc": {
                    "start": {
                      "line": 32,
                      "column": 1
                    },
                    "end": {
                      "line": 32,
                      "column": 9
                    }
                  }
                },
                "right": {
                  "type": "Identifier",
                  "name": "A",
                  "range": [
                    586,
                    587
                  ],
                  "loc": {
                    "start": {
                      "line": 32,
                      "column": 12
                    },
                    "end": {
                      "line": 32,
                      "column": 13
                    }
                  }
                },
                "range": [
                  575,
                  587
                ],
                "loc": {
                  "start": {
                    "line": 32,
                    "column": 1
                  },
                  "end": {
                    "line": 32,
                    "column": 13
                  }
                }
              },
              "range": [
                575,
                589
              ],
              "loc": {
                "start": {
                  "line": 32,
                  "column": 1
                },
                "end": {
                  "line": 32,
                  "column": 15
                }
              }
            }
          ],
          "range": [
            306,
            592
          ],
          "loc": {
            "start": {
              "line": 14,
              "column": 35
            },
            "end": {
              "line": 34,
              "column": 1
            }
          }
        },
        "generator": false,
        "expression": false,
        "range": [
          278,
          592
        ],
        "loc": {
          "start": {
            "line": 14,
            "column": 7
          },
          "end": {
            "line": 34,
            "column": 1
          }
        },
        "leadingComments": [
          {
            "type": "Block",
            "value": "*\n * Rotate tree right.\n * (see https://en.wikipedia.org/wiki/Tree_rotation)\n *\n *      B                A\n *     / \\              / \\\n *    A   c     ->     a   B\n *   / \\                  / \\\n *  a   b                b   c\n *\n * @param {Node} A root of the tree\n ",
            "range": [
              0,
              269
            ],
            "loc": {
              "start": {
                "line": 1,
                "column": 0
              },
              "end": {
                "line": 12,
                "column": 3
              }
            }
          }
        ],
        "trailingComments": []
      },
      "specifiers": [],
      "source": null,
      "range": [
        271,
        592
      ],
      "loc": {
        "start": {
          "line": 14,
          "column": 0
        },
        "end": {
          "line": 34,
          "column": 1
        }
      },
      "leadingComments": [
        {
          "type": "Block",
          "value": "*\n * Rotate tree right.\n * (see https://en.wikipedia.org/wiki/Tree_rotation)\n *\n *      B                A\n *     / \\              / \\\n *    A   c     ->     a   B\n *   / \\                  / \\\n *  a   b                b   c\n *\n * @param {Node} A root of the tree\n ",
          "range": [
            0,
            269
          ],
          "loc": {
            "start": {
              "line": 1,
              "column": 0
            },
            "end": {
              "line": 12,
              "column": 3
            }
          }
        }
      ]
    }
  ],
  "sourceType": "module",
  "range": [
    271,
    592
  ],
  "loc": {
    "start": {
      "line": 14,
      "column": 0
    },
    "end": {
      "line": 34,
      "column": 1
    }
  },
  "comments": [
    {
      "type": "Block",
      "value": "*\n * Rotate tree right.\n * (see https://en.wikipedia.org/wiki/Tree_rotation)\n *\n *      B                A\n *     / \\              / \\\n *    A   c     ->     a   B\n *   / \\                  / \\\n *  a   b                b   c\n *\n * @param {Node} A root of the tree\n ",
      "range": [
        0,
        269
      ],
      "loc": {
        "start": {
          "line": 1,
          "column": 0
        },
        "end": {
          "line": 12,
          "column": 3
        }
      }
    }
  ]
}